{
  "consumer": {
    "name": "PHPBackendConsumer"
  },
  "interactions": [
    {
      "description": "A request for user details",
      "providerStates": [
        {
          "name": "A user with ID 1 exists"
        }
      ],
      "request": {
        "method": "GET",
        "path": "/api/users/1"
      },
      "response": {
        "body": {
          "email": "john.doe@example.com",
          "id": 1
        },
        "headers": {
          "Content-Type": "application/json"
        },
        "matchingRules": {
          "body": {
            "$.email": {
              "combine": "AND",
              "matchers": [
                {
                  "match": "type"
                }
              ]
            },
            "$.id": {
              "combine": "AND",
              "matchers": [
                {
                  "match": "type"
                }
              ]
            }
          }
        },
        "status": 200
      }
    }
  ],
  "metadata": {
    "pactRust": {
      "ffi": "0.4.26",
      "mockserver": "1.2.11",
      "models": "1.2.7"
    },
    "pactSpecification": {
      "version": "3.0.0"
    }
  },
  "provider": {
    "name": "Backend"
  }
}